Hosein_Tabr/An_Wb.py
Hosein_Tabr/Clien.py
Hosein_Tabr/Copyright.py
Hosein_Tabr/Device.py
Hosein_Tabr/Encoder.py
Hosein_Tabr/Error.py
Hosein_Tabr/Getheader.py
Hosein_Tabr/GtM.py
Hosein_Tabr/Hosein_Tabr.py
Hosein_Tabr/PostData.py
Hosein_Tabr/Robino.py
Hosein_Tabr/TypeText.py
Hosein_Tabr/__init__.py
Hosein_Tabr/encryption.py
Hosein_Tabr/zed.py
Hosein_Tabr-4.7.5.dist-info/METADATA
Hosein_Tabr-4.7.5.dist-info/WHEEL
Hosein_Tabr-4.7.5.dist-info/top_level.txt
Hosein_Tabr-4.7.5.dist-info/RECORD
