Metadata-Version: 2.1
Name: Hosein-Tabr
Version: 4.7.5
Summary: Robot smart
Home-page: https://github.com/pypa/sampleproject
Author-email: 09014719950qwer@gmail.com
Keywords: Hosein,Hosein_tabr,Hosein-tabr,hosein_tabr,bot,Bot,BOT,Robot,ROBOT,robot,rubika,Rubika,Python
Classifier: Development Status :: 3 - Alpha
Classifier: Intended Audience :: Developers
Classifier: Topic :: Software Development :: Build Tools
Classifier: License :: OSI Approved :: MIT License
Classifier: Programming Language :: Python :: Implementation :: PyPy
Classifier: Programming Language :: Python :: 3
Classifier: Programming Language :: Python :: 3.4
Classifier: Programming Language :: Python :: 3.5
Classifier: Programming Language :: Python :: 3.6
Classifier: Programming Language :: Python :: 3.7
Classifier: Programming Language :: Python :: 3.8
Classifier: Programming Language :: Python :: 3.9
Classifier: Programming Language :: Python :: 3.10
Classifier: Programming Language :: Python :: 3.11
